{"pixiv_pic": [{"name": "115609986", "path": "./pixiv/2024-02-01-14-08-13/115609986.jpg", "index": 0, "user": "\u307f\u306a\u306f\u3080", "ext": ".jpg"}, {"name": "115614287", "path": "./pixiv/2024-02-01-14-08-13/115614287.png", "index": 1, "user": "\u30eb\u30b7\u30e5", "ext": ".png"}, {"name": "115602646", "path": "./pixiv/2024-02-01-14-08-13/115602646.jpg", "index": 2, "user": "Ame\u3082\u3061\u1d55\u03082\ud83c\udf6d", "ext": ".jpg"}, {"name": "115638841", "path": "./pixiv/2024-02-01-14-08-13/115638841.jpg", "index": 3, "user": "Taroco", "ext": ".jpg"}, {"name": "115604704", "path": "./pixiv/2024-02-01-14-08-13/115604704.jpg", "index": 4, "user": "s", "ext": ".jpg"}, {"name": "115624537", "path": "./pixiv/2024-02-01-14-08-13/115624537.jpg", "index": 5, "user": "\u3075\u308f\u308a", "ext": ".jpg"}, {"name": "115599983", "path": "./pixiv/2024-02-01-14-08-13/115599983.png", "index": 6, "user": "Chaesu", "ext": ".png"}, {"name": "115598276", "path": "./pixiv/2024-02-01-14-08-13/115598276.png", "index": 7, "user": "helloimtea", "ext": ".png"}, {"name": "115601436", "path": "./pixiv/2024-02-01-14-08-13/115601436.jpg", "index": 8, "user": "Jesse", "ext": ".jpg"}, {"name": "115597918", "path": "./pixiv/2024-02-01-14-08-13/115597918.jpg", "index": 9, "user": "RIKO", "ext": ".jpg"}, {"name": "115603930", "path": "./pixiv/2024-02-01-14-08-13/115603930.jpg", "index": 10, "user": "\u6f2b\u753b\u7d20\u6750\u5de5\u623f", "ext": ".jpg"}, {"name": "115618501", "path": "./pixiv/2024-02-01-14-08-13/115618501.jpg", "index": 11, "user": "\u3086\u305a\u3091\u306a", "ext": ".jpg"}, {"name": "115635362", "path": "./pixiv/2024-02-01-14-08-13/115635362.jpg", "index": 12, "user": "8810\uff5cHayato", "ext": ".jpg"}, {"name": "115600493", "path": "./pixiv/2024-02-01-14-08-13/115600493.jpg", "index": 13, "user": "\u4e0a\u5c71\u9053\u90ce", "ext": ".jpg"}, {"name": "115630674", "path": "./pixiv/2024-02-01-14-08-13/115630674.png", "index": 14, "user": "\u3064\u306d@FANBOX\u59cb\u3081\u307e\u3057\u305f", "ext": ".png"}, {"name": "115617764", "path": "./pixiv/2024-02-01-14-08-13/115617764.png", "index": 15, "user": "\u30c1\u30e3\u30a4", "ext": ".png"}, {"name": "115624859", "path": "./pixiv/2024-02-01-14-08-13/115624859.jpg", "index": 16, "user": "\u4e5d\u5341\u4e5d", "ext": ".jpg"}, {"name": "115615853", "path": "./pixiv/2024-02-01-14-08-13/115615853.jpg", "index": 17, "user": "\u30b4\u30eb\u30b4\u30f3\u30be\u30fc\u30e9", "ext": ".jpg"}, {"name": "115621040", "path": "./pixiv/2024-02-01-14-08-13/115621040.png", "index": 18, "user": "\u30e6\u30d2", "ext": ".png"}, {"name": "115615387", "path": "./pixiv/2024-02-01-14-08-13/115615387.jpg", "index": 19, "user": "\u304b\u306b\u30d3\u30fc\u30e0", "ext": ".jpg"}, {"name": "115611929", "path": "./pixiv/2024-02-01-14-08-13/115611929.jpg", "index": 20, "user": "Salmon88", "ext": ".jpg"}, {"name": "115642155", "path": "./pixiv/2024-02-01-14-08-13/115642155.jpg", "index": 21, "user": "\u30ab\u30b3\u30df\u30b9\u30eb", "ext": ".jpg"}, {"name": "115608407", "path": "./pixiv/2024-02-01-14-08-13/115608407.jpg", "index": 22, "user": "Puracotte\uff0a\u3077\u3089\u3053", "ext": ".jpg"}, {"name": "115621982", "path": "./pixiv/2024-02-01-14-08-13/115621982.png", "index": 23, "user": "\ud83d\udc1f", "ext": ".png"}, {"name": "115624422", "path": "./pixiv/2024-02-01-14-08-13/115624422.jpg", "index": 24, "user": "\u30b9\u30b3\u30c3\u30c6\u30a3", "ext": ".jpg"}, {"name": "115613421", "path": "./pixiv/2024-02-01-14-08-13/115613421.jpg", "index": 25, "user": "hakusetu", "ext": ".jpg"}, {"name": "115638533", "path": "./pixiv/2024-02-01-14-08-13/115638533.png", "index": 26, "user": "\u6afb\u65e5\u548c\u9b8e\u5b9f\u3000\u9023\u8f09\u4e2d", "ext": ".png"}, {"name": "115619946", "path": "./pixiv/2024-02-01-14-08-13/115619946.jpg", "index": 27, "user": "\u3089\u3044\u3089\u3063\u304f", "ext": ".jpg"}, {"name": "115599653", "path": "./pixiv/2024-02-01-14-08-13/115599653.jpg", "index": 28, "user": "\u305b\u3089\u306a\u308b", "ext": ".jpg"}, {"name": "115617800", "path": "./pixiv/2024-02-01-14-08-13/115617800.jpg", "index": 29, "user": "\u5f69\u8389\u308f\u3089\u3073", "ext": ".jpg"}, {"name": "115612267", "path": "./pixiv/2024-02-01-14-08-13/115612267.png", "index": 30, "user": "saihate", "ext": ".png"}, {"name": "115602328", "path": "./pixiv/2024-02-01-14-08-13/115602328.png", "index": 31, "user": "Sciamano240", "ext": ".png"}, {"name": "115612931", "path": "./pixiv/2024-02-01-14-08-13/115612931.png", "index": 32, "user": "\u5c71\u91ce\u3046\u3065\u307f", "ext": ".png"}, {"name": "115610073", "path": "./pixiv/2024-02-01-14-08-13/115610073.jpg", "index": 33, "user": "syuri22", "ext": ".jpg"}, {"name": "115640815", "path": "./pixiv/2024-02-01-14-08-13/115640815.png", "index": 34, "user": "Vardan", "ext": ".png"}, {"name": "115597873", "path": "./pixiv/2024-02-01-14-08-13/115597873.jpg", "index": 35, "user": "\u30b7\u30e7\u30c3\u30c8\u30ac\u30f3\u30de\u30f3", "ext": ".jpg"}, {"name": "115597815", "path": "./pixiv/2024-02-01-14-08-13/115597815.jpg", "index": 36, "user": "mell\u00b0@\u304a\u4ed5\u4e8b\u52df\u96c6\u4e2d", "ext": ".jpg"}, {"name": "115624355", "path": "./pixiv/2024-02-01-14-08-13/115624355.png", "index": 37, "user": "Mika1Pikazo", "ext": ".png"}, {"name": "115605866", "path": "./pixiv/2024-02-01-14-08-13/115605866.png", "index": 38, "user": "\u82b1\u591c3(\u306f\u306a\u3084)", "ext": ".png"}, {"name": "115618059", "path": "./pixiv/2024-02-01-14-08-13/115618059.png", "index": 39, "user": "YHM", "ext": ".png"}, {"name": "115597729", "path": "./pixiv/2024-02-01-14-08-13/115597729.jpg", "index": 40, "user": "Sa-fu", "ext": ".jpg"}]}